incise/__init__.py
incise/core.py
incise/helpers.py
incise/vendor.py
incise-1.1.0.dist-info/LICENCE
incise-1.1.0.dist-info/METADATA
incise-1.1.0.dist-info/WHEEL
incise-1.1.0.dist-info/entry_points.txt
incise-1.1.0.dist-info/top_level.txt
incise-1.1.0.dist-info/RECORD
